Workbook

Sheet Dashboard
N1: =SUMPRODUCT(Base_Dados!$H$2:$H$501,--IF($B$8="All",1,Base_Dados!$C$2:$C$501=$B$8),--IF($D$8="All",1,Base_Dados!$I$2:$I$501=$D$8))
B2: XBOX GAME PASS — SALES DASHBOARD | N2: =SUMPRODUCT(--IF($B$8="All",1,Base_Dados!$C$2:$C$501=$B$8),--IF($D$8="All",1,Base_Dados!$I$2:$I$501=$D$8))
N3: =IF(N2=0,0,N1/N2)
B4: Performance overview • 2024 subscriber dataset | J4: Base de Dados | K4: Análises | L4: README
B6: FILTROS
B7: Subscription Type | D7: Auto Renewal
B8: All | D8: All
B10: TOTAL REVENUE | F10: SUBSCRIBERS | J10: AVG. REVENUE / SUBSCRIBER
B11: =N1 | F11: =N2 | J11: =N3
J28: GUIA DE LEITURA • Compare os planos pelo faturamento. • Veja quais add-ons aparecem com maior frequência. • Avalie a proporção de renovação automática. • Observe a evolução mensal para identificar tendências. Use os filtros no topo para explorar a base.

Sheet Base_Dados
A1: Subscriber ID | B1: Start Date | C1: Subscription Type | D1: Plan Price (USD) | E1: Add-on | F1: Add-on Value (USD) | G1: Discount (USD) | H1: Revenue (USD) | I1: Auto Renewal | J1: Payment Method | K1: Country | L1: Age | M1: End Date
A2: XGP-0001 | B2: 45619 | C2: Core | D2: 9.99 | E2: EA Play | F2: 4.99 | G2: 0 | H2: 14.98 | I2: Yes | J2: Credit Card | K2: Mexico | L2: 23 | M2: 45984
A3: XGP-0002 | B3: 45508 | C3: Core | D3: 9.99 | E3: None | F3: 0 | G3: 0 | H3: 9.99 | I3: Yes | J3: Credit Card | K3: Mexico | L3: 30 | M3: 45873
A4: XGP-0003 | B4: 45624 | C4: Ultimate | D4: 19.99 | E4: None | F4: 0 | G4: 1 | H4: 18.99 | I4: Yes | J4: Credit Card | K4: Canada | L4: 62 | M4: 45714
A5: XGP-0004 | B5: 45466 | C5: Standard | D5: 14.99 | E5: None | F5: 0 | G5: 0 | H5: 14.99 | I5: Yes | J5: Gift Card | K5: United States | L5: 40 | M5: 45556
A6: XGP-0005 | B6: 45601 | C6: Standard | D6: 14.99 | E6: None | F6: 0 | G6: 1 | H6: 13.99 | I6: Yes | J6: Gift Card | K6: United States | L6: 53 | M6: 45691
A7: XGP-0006 | B7: 45613 | C7: Standard | D7: 14.99 | E7: Minecraft Season Pass | F7: 3.99 | G7: 2 | H7: 16.98 | I7: Yes | J7: Credit Card | K7: United States | L7: 60 | M7: 45643
A8: XGP-0007 | B8: 45440 | C8: Ultimate | D8: 19.99 | E8: Minecraft Season Pass | F8: 3.99 | G8: 0 | H8: 23.98 | I8: Yes | J8: Gift Card | K8: United Kingdom | L8: 28 | M8: 45530
A9: XGP-0008 | B9: 45473 | C9: Core | D9: 9.99 | E9: None | F9: 0 | G9: 0 | H9: 9.99 | I9: Yes | J9: Debit Card | K9: Mexico | L9: 33 | M9: 45503
A10: XGP-0009 | B10: 45528 | C10: Standard | D10: 14.99 | E10: EA Play + Minecraft | F10: 7.99 | G10: 2 | H10: 20.98 | I10: Yes | J10: PayPal | K10: United States | L10: 32 | M10: 45558
A11: XGP-0010 | B11: 45453 | C11: Standard | D11: 14.99 | E11: None | F11: 0 | G11: 2 | H11: 12.99 | I11: No | J11: PayPal | K11: Canada | L11: 59 | M11: 45543
A12: XGP-0011 | B12: 45494 | C12: Ultimate | D12: 19.99 | E12: EA Play | F12: 4.99 | G12: 0 | H12: 24.98 | I12: Yes | J12: Debit Card | K12: Mexico | L12: 52 | M12: 45584
A13: XGP-0012 | B13: 45591 | C13: Standard | D13: 14.99 | E13: EA Play | F13: 4.99 | G13: 0 | H13: 19.98 | I13: Yes | J13: Debit Card | K13: Mexico | L13: 49 | M13: 45621
... A501: XGP-0500 | B501: 45593 | C501: Ultimate | D501: 19.99 | E501: None | F501: 0 | G501: 1 | H501: 18.99 | I501: Yes | J501: Credit Card | K501: Brazil | L501: 41 | M501: 45958

Sheet Listas
A2: Core | B2: All
A3: Standard | B3: Yes
A4: Ultimate | B4: No

Sheet Análises
A1: ANÁLISES
A3: Plano | B3: Assinantes | C3: Receita (USD) | E3: Add-on | F3: Assinantes | G3: Receita adicional (USD) | I3: Auto Renewal | J3: Assinantes | K3: Receita (USD)
A4: Core | B4: =COUNTIF(Base_Dados!$C$2:$C$501,A4) | C4: =SUMIF(Base_Dados!$C$2:$C$501,A4,Base_Dados!$H$2:$H$501) | E4: None | F4: =COUNTIF(Base_Dados!$E$2:$E$501,E4) | G4: =SUMIF(Base_Dados!$E$2:$E$501,E4,Base_Dados!$F$2:$F$501) | I4: Yes | J4: =COUNTIF(Base_Dados!$I$2:$I$501,I4) | K4: =SUMIF(Base_Dados!$I$2:$I$501,I4,Base_Dados!$H$2:$H$501)
A5: Standard | B5: =COUNTIF(Base_Dados!$C$2:$C$501,A5) | C5: =SUMIF(Base_Dados!$C$2:$C$501,A5,Base_Dados!$H$2:$H$501) | E5: EA Play | F5: =COUNTIF(Base_Dados!$E$2:$E$501,E5) | G5: =SUMIF(Base_Dados!$E$2:$E$501,E5,Base_Dados!$F$2:$F$501) | I5: No | J5: =COUNTIF(Base_Dados!$I$2:$I$501,I5) | K5: =SUMIF(Base_Dados!$I$2:$I$501,I5,Base_Dados!$H$2:$H$501)
A6: Ultimate | B6: =COUNTIF(Base_Dados!$C$2:$C$501,A6) | C6: =SUMIF(Base_Dados!$C$2:$C$501,A6,Base_Dados!$H$2:$H$501) | E6: Minecraft Season Pass | F6: =COUNTIF(Base_Dados!$E$2:$E$501,E6) | G6: =SUMIF(Base_Dados!$E$2:$E$501,E6,Base_Dados!$F$2:$F$501)
E7: EA Play + Minecraft | F7: =COUNTIF(Base_Dados!$E$2:$E$501,E7) | G7: =SUMIF(Base_Dados!$E$2:$E$501,E7,Base_Dados!$F$2:$F$501)
A10: Mês | B10: Receita (USD) | C10: Assinantes
A11: 45292 | B11: =SUMIFS(Base_Dados!$H$2:$H$501,Base_Dados!$B$2:$B$501,">="&A11,Base_Dados!$B$2:$B$501,"<"&EDATE(A11,1)) | C11: =COUNTIFS(Base_Dados!$B$2:$B$501,">="&A11,Base_Dados!$B$2:$B$501,"<"&EDATE(A11,1))
A12: 45323 | B12: =SUMIFS(Base_Dados!$H$2:$H$501,Base_Dados!$B$2:$B$501,">="&A12,Base_Dados!$B$2:$B$501,"<"&EDATE(A12,1)) | C12: =COUNTIFS(Base_Dados!$B$2:$B$501,">="&A12,Base_Dados!$B$2:$B$501,"<"&EDATE(A12,1))
A13: 45352 | B13: =SUMIFS(Base_Dados!$H$2:$H$501,Base_Dados!$B$2:$B$501,">="&A13,Base_Dados!$B$2:$B$501,"<"&EDATE(A13,1)) | C13: =COUNTIFS(Base_Dados!$B$2:$B$501,">="&A13,Base_Dados!$B$2:$B$501,"<"&EDATE(A13,1))
A14: 45383 | B14: =SUMIFS(Base_Dados!$H$2:$H$501,Base_Dados!$B$2:$B$501,">="&A14,Base_Dados!$B$2:$B$501,"<"&EDATE(A14,1)) | C14: =COUNTIFS(Base_Dados!$B$2:$B$501,">="&A14,Base_Dados!$B$2:$B$501,"<"&EDATE(A14,1))
A15: 45413 | B15: =SUMIFS(Base_Dados!$H$2:$H$501,Base_Dados!$B$2:$B$501,">="&A15,Base_Dados!$B$2:$B$501,"<"&EDATE(A15,1)) | C15: =COUNTIFS(Base_Dados!$B$2:$B$501,">="&A15,Base_Dados!$B$2:$B$501,"<"&EDATE(A15,1))
A16: 45444 | B16: =SUMIFS(Base_Dados!$H$2:$H$501,Base_Dados!$B$2:$B$501,">="&A16,Base_Dados!$B$2:$B$501,"<"&EDATE(A16,1)) | C16: =COUNTIFS(Base_Dados!$B$2:$B$501,">="&A16,Base_Dados!$B$2:$B$501,"<"&EDATE(A16,1))
A17: 45474 | B17: =SUMIFS(Base_Dados!$H$2:$H$501,Base_Dados!$B$2:$B$501,">="&A17,Base_Dados!$B$2:$B$501,"<"&EDATE(A17,1)) | C17: =COUNTIFS(Base_Dados!$B$2:$B$501,">="&A17,Base_Dados!$B$2:$B$501,"<"&EDATE(A17,1))
A18: 45505 | B18: =SUMIFS(Base_Dados!$H$2:$H$501,Base_Dados!$B$2:$B$501,">="&A18,Base_Dados!$B$2:$B$501,"<"&EDATE(A18,1)) | C18: =COUNTIFS(Base_Dados!$B$2:$B$501,">="&A18,Base_Dados!$B$2:$B$501,"<"&EDATE(A18,1))
A19: 45536 | B19: =SUMIFS(Base_Dados!$H$2:$H$501,Base_Dados!$B$2:$B$501,">="&A19,Base_Dados!$B$2:$B$501,"<"&EDATE(A19,1)) | C19: =COUNTIFS(Base_Dados!$B$2:$B$501,">="&A19,Base_Dados!$B$2:$B$501,"<"&EDATE(A19,1))
A20: 45566 | B20: =SUMIFS(Base_Dados!$H$2:$H$501,Base_Dados!$B$2:$B$501,">="&A20,Base_Dados!$B$2:$B$501,"<"&EDATE(A20,1)) | C20: =COUNTIFS(Base_Dados!$B$2:$B$501,">="&A20,Base_Dados!$B$2:$B$501,"<"&EDATE(A20,1))
A21: 45597 | B21: =SUMIFS(Base_Dados!$H$2:$H$501,Base_Dados!$B$2:$B$501,">="&A21,Base_Dados!$B$2:$B$501,"<"&EDATE(A21,1)) | C21: =COUNTIFS(Base_Dados!$B$2:$B$501,">="&A21,Base_Dados!$B$2:$B$501,"<"&EDATE(A21,1))
A22: 45627 | B22: =SUMIFS(Base_Dados!$H$2:$H$501,Base_Dados!$B$2:$B$501,">="&A22,Base_Dados!$B$2:$B$501,"<"&EDATE(A22,1)) | C22: =COUNTIFS(Base_Dados!$B$2:$B$501,">="&A22,Base_Dados!$B$2:$B$501,"<"&EDATE(A22,1))

Sheet README
A1: README — Dashboard de Vendas do Xbox
A3: Objetivo
A4: Dashboard de vendas do Xbox Game Pass criado no Excel para transformar uma base de assinaturas em indicadores visuais úteis para análise.
A6: Visões
A7: Receita total, quantidade de assinantes, receita média, receita por plano, add-ons, renovação automática e evolução mensal.
A9: Recursos
A10: Tabela estruturada, filtros, validação de dados, fórmulas, KPIs, gráficos e navegação entre abas.
A12: Abas
A13: Dashboard | Base_Dados | Análises | Listas | README
A15: Dados
A16: A base oficial é disponibilizada pela DIO. Como o download externo não ficou acessível neste ambiente, a entrega usa 500 registros demonstrativos com a mesma lógica de negócio do desafio. A aba Base_Dados pode ser substituída pelos dados oficiais mantendo os cabeçalhos.
A18: Como usar
... A25: https://hermes.dio.me/files/assets/805d54f9-6d53-4246-bed7-4aa2da615923.xlsx
